AutoOpenApi/__init__.py
AutoOpenApi/autoopenapi.py
AutoOpenApi-1.2.0.dist-info/LICENSE
AutoOpenApi-1.2.0.dist-info/METADATA
AutoOpenApi-1.2.0.dist-info/WHEEL
AutoOpenApi-1.2.0.dist-info/top_level.txt
AutoOpenApi-1.2.0.dist-info/RECORD
