Metadata-Version: 2.1
Name: AutoOpenApi
Version: 1.2.0
Summary: An attempt to go from test definition to openapi3 spec
Home-page: https://github.com/JarrodMccarthy/AutoOpenApi
Author: Jarrod McCarthy
Author-email: jarrodmccarthy12@gmail.com
Project-URL: Bug Tracker, https://github.com/JarrodMccarthy/AutoOpenApi/issues
Classifier: Programming Language :: Python :: 3
Classifier: License :: OSI Approved :: MIT License
Classifier: Operating System :: OS Independent
Requires-Python: >=3.6
License-File: LICENSE
